prbdes/data/exclude/excl_roi_1.bed
prbdes/data/exclude/excl_roi_10.bed
prbdes/data/exclude/excl_roi_11.bed
prbdes/data/exclude/excl_roi_12.bed
prbdes/data/exclude/excl_roi_2.bed
prbdes/data/exclude/excl_roi_3.bed
prbdes/data/exclude/excl_roi_4.bed
prbdes/data/exclude/excl_roi_5.bed
prbdes/data/exclude/excl_roi_6.bed
prbdes/data/exclude/excl_roi_7.bed
prbdes/data/exclude/excl_roi_8.bed
prbdes/data/exclude/excl_roi_9.bed
prbdes/data/rois/DNA_FISH_template.ods
prbdes/data/rois/DNA_RNA_FISH_template.ods
prbdes/data/rois/RNA_FISH_template.ods
prbdes/data/rois/all_regions.tsv
prbdes/data/rois/df_DNA_FISH.txt
prbdes/data/rois/df_DNA_RNA_FISH.txt
prbdes/data/rois/df_RNA_FISH.txt
prbdes/main.py
prbdes/notebooks/plot_oligos.ipynb
prbdes/notebooks/plot_probe_candidates.ipynb
prbdes/notebooks/plot_probes.ipynb
prbdes/shell/apply_blacklist.sh
prbdes/shell/build-db.sh
prbdes/shell/build-db_BL.sh
prbdes/shell/build-db_cc.sh
prbdes/shell/generate_blacklist.sh
prbdes/shell/get_ref_genome.sh
prbdes/shell/melt_secs_parallel.sh
prbdes/shell/pipeline.sh
prbdes/shell/pipeline_exclude.sh
prbdes/shell/probe-query.sh
prbdes/shell/run_nHUSH.sh
prbdes/shell/run_nHUSH_excl.sh
prbdes/shell/unfinished_HUSH.sh
prbdes/shell/validation_oldHUSH_BLAST.sh
prbdes/src/HUSH_feedback.py
prbdes/src/cycling_query.py
prbdes/src/escafish_score.py
prbdes/src/exclude_region.py
prbdes/src/generate_exclude.py
prbdes/src/get_oligos.py
prbdes/src/prepare_input.r
prbdes/src/reform_hush.py
prbdes/src/reform_hush_combined.py
prbdes/src/reform_hush_consec.py
prbdes/src/select_probe.py
prbdes/src/split_fasta.py
prbdes/src/summarize-probes-cumul.py
prbdes/src/summarize-probes-final.py
prbdes/src/summarize-probes.py
prbdes-0.1.2.dist-info/LICENSE.txt
prbdes-0.1.2.dist-info/METADATA
prbdes-0.1.2.dist-info/WHEEL
prbdes-0.1.2.dist-info/entry_points.txt
prbdes-0.1.2.dist-info/RECORD
