Metadata-Version: 2.1
Name: prbdes
Version: 0.1.2
Summary: Probe design originails for FISH by Quentin Verron
License: CC NC BY 4.0
Author: Quentin Verron
Maintainer: Quentin Verron
Requires-Python: >=3.10,<4.0
Classifier: License :: Other/Proprietary License
Classifier: Programming Language :: Python :: 3
Classifier: Programming Language :: Python :: 3.10
Classifier: Programming Language :: Python :: 3.11
Classifier: Programming Language :: Python :: 3.12
Requires-Dist: biopython (>=1.82,<2.0)
Requires-Dist: click (>=8.1.0,<9.0.0)
Requires-Dist: ifpd2q (>=1.0.3,<2.0.0)
Requires-Dist: joblib (>=1,<2)
Requires-Dist: numpy (>=1.20,<2.0)
Requires-Dist: pandas (>=1.2.2,<3.0)
Requires-Dist: poetry (>=1.5,<2.0)
Requires-Dist: requests (>=2.31.0,<3.0.0)
Requires-Dist: tabulate (>=0.9.0,<0.10.0)
Requires-Dist: tqdm (>=4,<5)
